[
  {
    "title": "Masterful Sketches",
    "description": "Discover the art of precision and detail with captivating sketches that tell a story.",
    "image": "https://i.ibb.co/F7PHpcg/painting-4159435-1280.jpg"
  },
  {
    "title": "Abstract Wonders",
    "description": "Dive into a realm of abstract beauty, where shapes and colors blend to create unique masterpieces.",
    "image": "https://i.ibb.co/SRthX38/brushes-3129361-1280.jpg"
  },
  {
    "title": "Nature's Palette",
    "description": "Immerse yourself in the soothing hues and organic forms inspired by the natural world.",

    "image": "https://i.ibb.co/zGrTfRw/to-dye-5821297-1280.jpg"
  },
  {
    "title": "Vibrant Creations",
    "description": "Explore a world of bold colors and expressive strokes that bring your imagination to life.",
    "image": "https://i.ibb.co/dcNHLFW/tulip-5060743-1280.jpg"
  },
  {
    "title": "Creative Journey",
    "description": "Join us on an artistic adventure and unleash your inner creativity with our exceptional works.",
    "image": "https://i.ibb.co/m41QnBS/brush-96240-1280.jpg"
  }
]
